{
  "project_info": {
    "project_number": "167726081008",
    "project_id": "nguyen-ngoc-tuong-manager-book",
    "storage_bucket": "nguyen-ngoc-tuong-manager-book.appspot.com"
  },
  "client": [
    {
      "client_info": {
        "mobilesdk_app_id": "1:167726081008:android:6fcf31a3b15053976cf335",
        "android_client_info": {
          "package_name": "com.nttuong.managerbook"
        }
      },
      "oauth_client": [
        {
          "client_id": "167726081008-9do2b227ak6lhtaqmogniv3qn30qkqsl.apps.googleusercontent.com",
          "client_type": 3
        }
      ],
      "api_key": [
        {
          "current_key": "AIzaSyDWbJoC5ARnLlxQn7l0Gdhp9lBjxaHTj2k"
        }
      ],
      "services": {
        "appinvite_service": {
          "other_platform_oauth_client": [
            {
              "client_id": "167726081008-9do2b227ak6lhtaqmogniv3qn30qkqsl.apps.googleusercontent.com",
              "client_type": 3
            }
          ]
        }
      }
    }
  ],
  "configuration_version": "1"
}